pybase64_reddy/__init__.py
pybase64_reddy/cli.py
pybase64_reddy-0.1.0.dist-info/LICENSE
pybase64_reddy-0.1.0.dist-info/METADATA
pybase64_reddy-0.1.0.dist-info/WHEEL
pybase64_reddy-0.1.0.dist-info/entry_points.txt
pybase64_reddy-0.1.0.dist-info/top_level.txt
pybase64_reddy-0.1.0.dist-info/RECORD
