Metadata-Version: 2.1
Name: pybase64_reddy
Version: 0.1.0
Summary: A simple base64 encode/decode tool with a CLI.
Home-page: https://github.com/yourusername/pybase64_reddy
Author: Your Name
Author-email: your.email@example.com
Classifier: Programming Language :: Python :: 3
Classifier: License :: OSI Approved :: MIT License
Classifier: Operating System :: OS Independent
Requires-Python: >=3.6
License-File: LICENSE
